{
  "email": "jesse@leadmagic.io",
  "status": "valid",
  "credits_consumed": 1,
  "message": "Valid email found.",
  "first_name": "Jesse",
  "last_name": "Ouellette",
  "domain": "leadmagic.io",
  "is_domain_catch_all": false,
  "mx_record": "alt3.aspmx.l.google.com",
  "mx_provider": "Google Workspace",
  "mx_security_gateway": false,
  "company_name": "Leadmagic",
  "company_industry": "",
  "company_size": "11-50",
  "company_founded": 2022,
  "company_location": {
    "name": "boston, massachusetts, united states",
    "locality": "boston",
    "region": "massachusetts",
    "metro": "boston, massachusetts",
    "country": "united states",
    "continent": "north america",
    "street_address": "1 seaport lane",
    "address_line_2": null,
    "postal_code": "02210",
    "geo": "42.35,-71.06"
  },
  "company_linkedin_url": "linkedin.com/company/leadmagichq",
  "company_linkedin_id": "75153174",
  "company_facebook_url": "",
  "company_twitter_url": "",
  "company_type": "private"
}
